{
  "service": {
    "service": "shops",
    "serviceObject": {
      "name": "shops"
    },
    "provider": {
      "stage": "dev",
      "region": "us-east-1",
      "variableSyntax": "\\${([ ~:a-zA-Z0-9._'\",\\-\\/\\(\\)]+?)}",
      "name": "aws",
      "runtime": "nodejs6.10",
      "environment": {
        "DYNAMODB_TABLE": "shops-dev"
      },
      "iamRoleStatements": [
        {
          "Effect": "Allow",
          "Action": [
            "dynamodb:Query",
            "dynamodb:Scan",
            "dynamodb:GetItem",
            "dynamodb:PutItem",
            "dynamodb:UpdateItem",
            "dynamodb:DeleteItem"
          ],
          "Resource": "arn:aws:dynamodb:us-east-1:*:table/shops-dev"
        }
      ],
      "versionFunctions": true,
      "remoteFunctionData": null,
      "compiledCloudFormationTemplate": {
        "AWSTemplateFormatVersion": "2010-09-09",
        "Description": "The AWS CloudFormation template for this Serverless application",
        "Resources": {
          "ServerlessDeploymentBucket": {
            "Type": "AWS::S3::Bucket",
            "Properties": {
              "AccelerateConfiguration": {
                "AccelerationStatus": "Suspended"
              }
            }
          },
          "CreateLogGroup": {
            "Type": "AWS::Logs::LogGroup",
            "Properties": {
              "LogGroupName": "/aws/lambda/shops-dev-create"
            }
          },
          "ListLogGroup": {
            "Type": "AWS::Logs::LogGroup",
            "Properties": {
              "LogGroupName": "/aws/lambda/shops-dev-list"
            }
          },
          "GetLogGroup": {
            "Type": "AWS::Logs::LogGroup",
            "Properties": {
              "LogGroupName": "/aws/lambda/shops-dev-get"
            }
          },
          "UpdateLogGroup": {
            "Type": "AWS::Logs::LogGroup",
            "Properties": {
              "LogGroupName": "/aws/lambda/shops-dev-update"
            }
          },
          "DeleteLogGroup": {
            "Type": "AWS::Logs::LogGroup",
            "Properties": {
              "LogGroupName": "/aws/lambda/shops-dev-delete"
            }
          },
          "GetAllProductsLogGroup": {
            "Type": "AWS::Logs::LogGroup",
            "Properties": {
              "LogGroupName": "/aws/lambda/shops-dev-getAllProducts"
            }
          },
          "IamRoleLambdaExecution": {
            "Type": "AWS::IAM::Role",
            "Properties": {
              "AssumeRolePolicyDocument": {
                "Version": "2012-10-17",
                "Statement": [
                  {
                    "Effect": "Allow",
                    "Principal": {
                      "Service": [
                        "lambda.amazonaws.com"
                      ]
                    },
                    "Action": [
                      "sts:AssumeRole"
                    ]
                  }
                ]
              },
              "Policies": [
                {
                  "PolicyName": {
                    "Fn::Join": [
                      "-",
                      [
                        "dev",
                        "shops",
                        "lambda"
                      ]
                    ]
                  },
                  "PolicyDocument": {
                    "Version": "2012-10-17",
                    "Statement": [
                      {
                        "Effect": "Allow",
                        "Action": [
                          "logs:CreateLogStream"
                        ],
                        "Resource": [
                          {
                            "Fn::Sub": "arn:aws:logs:${AWS::Region}:${AWS::AccountId}:log-group:/aws/lambda/shops-dev-create:*"
                          },
                          {
                            "Fn::Sub": "arn:aws:logs:${AWS::Region}:${AWS::AccountId}:log-group:/aws/lambda/shops-dev-list:*"
                          },
                          {
                            "Fn::Sub": "arn:aws:logs:${AWS::Region}:${AWS::AccountId}:log-group:/aws/lambda/shops-dev-get:*"
                          },
                          {
                            "Fn::Sub": "arn:aws:logs:${AWS::Region}:${AWS::AccountId}:log-group:/aws/lambda/shops-dev-update:*"
                          },
                          {
                            "Fn::Sub": "arn:aws:logs:${AWS::Region}:${AWS::AccountId}:log-group:/aws/lambda/shops-dev-delete:*"
                          },
                          {
                            "Fn::Sub": "arn:aws:logs:${AWS::Region}:${AWS::AccountId}:log-group:/aws/lambda/shops-dev-getAllProducts:*"
                          }
                        ]
                      },
                      {
                        "Effect": "Allow",
                        "Action": [
                          "logs:PutLogEvents"
                        ],
                        "Resource": [
                          {
                            "Fn::Sub": "arn:aws:logs:${AWS::Region}:${AWS::AccountId}:log-group:/aws/lambda/shops-dev-create:*:*"
                          },
                          {
                            "Fn::Sub": "arn:aws:logs:${AWS::Region}:${AWS::AccountId}:log-group:/aws/lambda/shops-dev-list:*:*"
                          },
                          {
                            "Fn::Sub": "arn:aws:logs:${AWS::Region}:${AWS::AccountId}:log-group:/aws/lambda/shops-dev-get:*:*"
                          },
                          {
                            "Fn::Sub": "arn:aws:logs:${AWS::Region}:${AWS::AccountId}:log-group:/aws/lambda/shops-dev-update:*:*"
                          },
                          {
                            "Fn::Sub": "arn:aws:logs:${AWS::Region}:${AWS::AccountId}:log-group:/aws/lambda/shops-dev-delete:*:*"
                          },
                          {
                            "Fn::Sub": "arn:aws:logs:${AWS::Region}:${AWS::AccountId}:log-group:/aws/lambda/shops-dev-getAllProducts:*:*"
                          }
                        ]
                      },
                      {
                        "$ref": "$[\"service\"][\"provider\"][\"iamRoleStatements\"][0]"
                      }
                    ]
                  }
                }
              ],
              "Path": "/",
              "RoleName": {
                "Fn::Join": [
                  "-",
                  [
                    "shops",
                    "dev",
                    "us-east-1",
                    "lambdaRole"
                  ]
                ]
              }
            }
          },
          "CreateLambdaFunction": {
            "Type": "AWS::Lambda::Function",
            "Properties": {
              "Code": {
                "S3Bucket": {
                  "Ref": "ServerlessDeploymentBucket"
                },
                "S3Key": "serverless/shops/dev/1516571923348-2018-01-21T21:58:43.348Z/shops.zip"
              },
              "FunctionName": "shops-dev-create",
              "Handler": "create.create",
              "MemorySize": 1024,
              "Role": {
                "Fn::GetAtt": [
                  "IamRoleLambdaExecution",
                  "Arn"
                ]
              },
              "Runtime": "nodejs6.10",
              "Timeout": 6,
              "Environment": {
                "Variables": {
                  "DYNAMODB_TABLE": "shops-dev"
                }
              }
            },
            "DependsOn": [
              "CreateLogGroup",
              "IamRoleLambdaExecution"
            ]
          },
          "CreateLambdaVersionTaP6Y24u4WQpRh3Q19TqVCd3PdTv1XU9fkvll5ztXY": {
            "Type": "AWS::Lambda::Version",
            "DeletionPolicy": "Retain",
            "Properties": {
              "FunctionName": {
                "Ref": "CreateLambdaFunction"
              },
              "CodeSha256": "6gTom89qK2odPMhhFkGTd2EOZ+duMU44qK43kcGtbo8="
            }
          },
          "ListLambdaFunction": {
            "Type": "AWS::Lambda::Function",
            "Properties": {
              "Code": {
                "S3Bucket": {
                  "Ref": "ServerlessDeploymentBucket"
                },
                "S3Key": "serverless/shops/dev/1516571923348-2018-01-21T21:58:43.348Z/shops.zip"
              },
              "FunctionName": "shops-dev-list",
              "Handler": "list.list",
              "MemorySize": 1024,
              "Role": {
                "Fn::GetAtt": [
                  "IamRoleLambdaExecution",
                  "Arn"
                ]
              },
              "Runtime": "nodejs6.10",
              "Timeout": 6,
              "Environment": {
                "Variables": {
                  "DYNAMODB_TABLE": "shops-dev"
                }
              }
            },
            "DependsOn": [
              "ListLogGroup",
              "IamRoleLambdaExecution"
            ]
          },
          "ListLambdaVersionYWgAFUmBX6Yv5DRatevpWHUQur1NjDe820Exzs": {
            "Type": "AWS::Lambda::Version",
            "DeletionPolicy": "Retain",
            "Properties": {
              "FunctionName": {
                "Ref": "ListLambdaFunction"
              },
              "CodeSha256": "6gTom89qK2odPMhhFkGTd2EOZ+duMU44qK43kcGtbo8="
            }
          },
          "GetLambdaFunction": {
            "Type": "AWS::Lambda::Function",
            "Properties": {
              "Code": {
                "S3Bucket": {
                  "Ref": "ServerlessDeploymentBucket"
                },
                "S3Key": "serverless/shops/dev/1516571923348-2018-01-21T21:58:43.348Z/shops.zip"
              },
              "FunctionName": "shops-dev-get",
              "Handler": "get.get",
              "MemorySize": 1024,
              "Role": {
                "Fn::GetAtt": [
                  "IamRoleLambdaExecution",
                  "Arn"
                ]
              },
              "Runtime": "nodejs6.10",
              "Timeout": 6,
              "Environment": {
                "Variables": {
                  "DYNAMODB_TABLE": "shops-dev"
                }
              }
            },
            "DependsOn": [
              "GetLogGroup",
              "IamRoleLambdaExecution"
            ]
          },
          "GetLambdaVersionBH490l2TIYbIIs8R04LX8usYhs9pZbQoruYjNAQho": {
            "Type": "AWS::Lambda::Version",
            "DeletionPolicy": "Retain",
            "Properties": {
              "FunctionName": {
                "Ref": "GetLambdaFunction"
              },
              "CodeSha256": "6gTom89qK2odPMhhFkGTd2EOZ+duMU44qK43kcGtbo8="
            }
          },
          "UpdateLambdaFunction": {
            "Type": "AWS::Lambda::Function",
            "Properties": {
              "Code": {
                "S3Bucket": {
                  "Ref": "ServerlessDeploymentBucket"
                },
                "S3Key": "serverless/shops/dev/1516571923348-2018-01-21T21:58:43.348Z/shops.zip"
              },
              "FunctionName": "shops-dev-update",
              "Handler": "update.update",
              "MemorySize": 1024,
              "Role": {
                "Fn::GetAtt": [
                  "IamRoleLambdaExecution",
                  "Arn"
                ]
              },
              "Runtime": "nodejs6.10",
              "Timeout": 6,
              "Environment": {
                "Variables": {
                  "DYNAMODB_TABLE": "shops-dev"
                }
              }
            },
            "DependsOn": [
              "UpdateLogGroup",
              "IamRoleLambdaExecution"
            ]
          },
          "UpdateLambdaVersionUR0MMhmmXWk0FtdvKuPmiCfXG3zwSZJsW6H3IkcI": {
            "Type": "AWS::Lambda::Version",
            "DeletionPolicy": "Retain",
            "Properties": {
              "FunctionName": {
                "Ref": "UpdateLambdaFunction"
              },
              "CodeSha256": "6gTom89qK2odPMhhFkGTd2EOZ+duMU44qK43kcGtbo8="
            }
          },
          "DeleteLambdaFunction": {
            "Type": "AWS::Lambda::Function",
            "Properties": {
              "Code": {
                "S3Bucket": {
                  "Ref": "ServerlessDeploymentBucket"
                },
                "S3Key": "serverless/shops/dev/1516571923348-2018-01-21T21:58:43.348Z/shops.zip"
              },
              "FunctionName": "shops-dev-delete",
              "Handler": "delete.delete",
              "MemorySize": 1024,
              "Role": {
                "Fn::GetAtt": [
                  "IamRoleLambdaExecution",
                  "Arn"
                ]
              },
              "Runtime": "nodejs6.10",
              "Timeout": 6,
              "Environment": {
                "Variables": {
                  "DYNAMODB_TABLE": "shops-dev"
                }
              }
            },
            "DependsOn": [
              "DeleteLogGroup",
              "IamRoleLambdaExecution"
            ]
          },
          "DeleteLambdaVersionvECnbEVGRTEhyz4dZHVQV94L7DoqaHTKYMoxbu4zTew": {
            "Type": "AWS::Lambda::Version",
            "DeletionPolicy": "Retain",
            "Properties": {
              "FunctionName": {
                "Ref": "DeleteLambdaFunction"
              },
              "CodeSha256": "6gTom89qK2odPMhhFkGTd2EOZ+duMU44qK43kcGtbo8="
            }
          },
          "GetAllProductsLambdaFunction": {
            "Type": "AWS::Lambda::Function",
            "Properties": {
              "Code": {
                "S3Bucket": {
                  "Ref": "ServerlessDeploymentBucket"
                },
                "S3Key": "serverless/shops/dev/1516571923348-2018-01-21T21:58:43.348Z/shops.zip"
              },
              "FunctionName": "shops-dev-getAllProducts",
              "Handler": "getAllProducts.get",
              "MemorySize": 1024,
              "Role": {
                "Fn::GetAtt": [
                  "IamRoleLambdaExecution",
                  "Arn"
                ]
              },
              "Runtime": "nodejs6.10",
              "Timeout": 6,
              "Environment": {
                "Variables": {
                  "DYNAMODB_TABLE": "shops-dev"
                }
              }
            },
            "DependsOn": [
              "GetAllProductsLogGroup",
              "IamRoleLambdaExecution"
            ]
          },
          "GetAllProductsLambdaVersion8WqdNfBg60zIVyAnI2XO4kg7JgFBIlYK3fOSahkAu8": {
            "Type": "AWS::Lambda::Version",
            "DeletionPolicy": "Retain",
            "Properties": {
              "FunctionName": {
                "Ref": "GetAllProductsLambdaFunction"
              },
              "CodeSha256": "6gTom89qK2odPMhhFkGTd2EOZ+duMU44qK43kcGtbo8="
            }
          },
          "ApiGatewayRestApi": {
            "Type": "AWS::ApiGateway::RestApi",
            "Properties": {
              "Name": "dev-shops",
              "EndpointConfiguration": {
                "Types": [
                  "EDGE"
                ]
              }
            }
          },
          "ApiGatewayResourceShops": {
            "Type": "AWS::ApiGateway::Resource",
            "Properties": {
              "ParentId": {
                "Fn::GetAtt": [
                  "ApiGatewayRestApi",
                  "RootResourceId"
                ]
              },
              "PathPart": "shops",
              "RestApiId": {
                "Ref": "ApiGatewayRestApi"
              }
            }
          },
          "ApiGatewayResourceShopsIdVar": {
            "Type": "AWS::ApiGateway::Resource",
            "Properties": {
              "ParentId": {
                "Ref": "ApiGatewayResourceShops"
              },
              "PathPart": "{id}",
              "RestApiId": {
                "Ref": "ApiGatewayRestApi"
              }
            }
          },
          "ApiGatewayResourceShopsIdVarProducts": {
            "Type": "AWS::ApiGateway::Resource",
            "Properties": {
              "ParentId": {
                "Ref": "ApiGatewayResourceShopsIdVar"
              },
              "PathPart": "products",
              "RestApiId": {
                "Ref": "ApiGatewayRestApi"
              }
            }
          },
          "ApiGatewayMethodShopsOptions": {
            "Type": "AWS::ApiGateway::Method",
            "Properties": {
              "AuthorizationType": "NONE",
              "HttpMethod": "OPTIONS",
              "MethodResponses": [
                {
                  "StatusCode": "200",
                  "ResponseParameters": {
                    "method.response.header.Access-Control-Allow-Origin": true,
                    "method.response.header.Access-Control-Allow-Headers": true,
                    "method.response.header.Access-Control-Allow-Methods": true,
                    "method.response.header.Access-Control-Allow-Credentials": true
                  },
                  "ResponseModels": {}
                }
              ],
              "RequestParameters": {},
              "Integration": {
                "Type": "MOCK",
                "RequestTemplates": {
                  "application/json": "{statusCode:200}"
                },
                "IntegrationResponses": [
                  {
                    "StatusCode": "200",
                    "ResponseParameters": {
                      "method.response.header.Access-Control-Allow-Origin": "'*'",
                      "method.response.header.Access-Control-Allow-Headers": "'Content-Type,X-Amz-Date,Authorization,X-Api-Key,X-Amz-Security-Token,X-Amz-User-Agent'",
                      "method.response.header.Access-Control-Allow-Methods": "'OPTIONS,GET,POST'",
                      "method.response.header.Access-Control-Allow-Credentials": "'false'"
                    },
                    "ResponseTemplates": {
                      "application/json": ""
                    }
                  }
                ]
              },
              "ResourceId": {
                "Ref": "ApiGatewayResourceShops"
              },
              "RestApiId": {
                "Ref": "ApiGatewayRestApi"
              }
            }
          },
          "ApiGatewayMethodShopsIdVarOptions": {
            "Type": "AWS::ApiGateway::Method",
            "Properties": {
              "AuthorizationType": "NONE",
              "HttpMethod": "OPTIONS",
              "MethodResponses": [
                {
                  "StatusCode": "200",
                  "ResponseParameters": {
                    "method.response.header.Access-Control-Allow-Origin": true,
                    "method.response.header.Access-Control-Allow-Headers": true,
                    "method.response.header.Access-Control-Allow-Methods": true,
                    "method.response.header.Access-Control-Allow-Credentials": true
                  },
                  "ResponseModels": {}
                }
              ],
              "RequestParameters": {},
              "Integration": {
                "Type": "MOCK",
                "RequestTemplates": {
                  "application/json": "{statusCode:200}"
                },
                "IntegrationResponses": [
                  {
                    "StatusCode": "200",
                    "ResponseParameters": {
                      "method.response.header.Access-Control-Allow-Origin": "'*'",
                      "method.response.header.Access-Control-Allow-Headers": "'Content-Type,X-Amz-Date,Authorization,X-Api-Key,X-Amz-Security-Token,X-Amz-User-Agent'",
                      "method.response.header.Access-Control-Allow-Methods": "'OPTIONS,DELETE,PUT,GET'",
                      "method.response.header.Access-Control-Allow-Credentials": "'false'"
                    },
                    "ResponseTemplates": {
                      "application/json": ""
                    }
                  }
                ]
              },
              "ResourceId": {
                "Ref": "ApiGatewayResourceShopsIdVar"
              },
              "RestApiId": {
                "Ref": "ApiGatewayRestApi"
              }
            }
          },
          "ApiGatewayMethodShopsIdVarProductsOptions": {
            "Type": "AWS::ApiGateway::Method",
            "Properties": {
              "AuthorizationType": "NONE",
              "HttpMethod": "OPTIONS",
              "MethodResponses": [
                {
                  "StatusCode": "200",
                  "ResponseParameters": {
                    "method.response.header.Access-Control-Allow-Origin": true,
                    "method.response.header.Access-Control-Allow-Headers": true,
                    "method.response.header.Access-Control-Allow-Methods": true,
                    "method.response.header.Access-Control-Allow-Credentials": true
                  },
                  "ResponseModels": {}
                }
              ],
              "RequestParameters": {},
              "Integration": {
                "Type": "MOCK",
                "RequestTemplates": {
                  "application/json": "{statusCode:200}"
                },
                "IntegrationResponses": [
                  {
                    "StatusCode": "200",
                    "ResponseParameters": {
                      "method.response.header.Access-Control-Allow-Origin": "'*'",
                      "method.response.header.Access-Control-Allow-Headers": "'Content-Type,X-Amz-Date,Authorization,X-Api-Key,X-Amz-Security-Token,X-Amz-User-Agent'",
                      "method.response.header.Access-Control-Allow-Methods": "'OPTIONS,GET'",
                      "method.response.header.Access-Control-Allow-Credentials": "'false'"
                    },
                    "ResponseTemplates": {
                      "application/json": ""
                    }
                  }
                ]
              },
              "ResourceId": {
                "Ref": "ApiGatewayResourceShopsIdVarProducts"
              },
              "RestApiId": {
                "Ref": "ApiGatewayRestApi"
              }
            }
          },
          "ApiGatewayMethodShopsPost": {
            "Type": "AWS::ApiGateway::Method",
            "Properties": {
              "HttpMethod": "POST",
              "RequestParameters": {},
              "ResourceId": {
                "Ref": "ApiGatewayResourceShops"
              },
              "RestApiId": {
                "Ref": "ApiGatewayRestApi"
              },
              "ApiKeyRequired": false,
              "AuthorizationType": "NONE",
              "Integration": {
                "IntegrationHttpMethod": "POST",
                "Type": "AWS_PROXY",
                "Uri": {
                  "Fn::Join": [
                    "",
                    [
                      "arn:aws:apigateway:",
                      {
                        "Ref": "AWS::Region"
                      },
                      ":lambda:path/2015-03-31/functions/",
                      {
                        "Fn::GetAtt": [
                          "CreateLambdaFunction",
                          "Arn"
                        ]
                      },
                      "/invocations"
                    ]
                  ]
                }
              },
              "MethodResponses": []
            }
          },
          "ApiGatewayMethodShopsGet": {
            "Type": "AWS::ApiGateway::Method",
            "Properties": {
              "HttpMethod": "GET",
              "RequestParameters": {},
              "ResourceId": {
                "Ref": "ApiGatewayResourceShops"
              },
              "RestApiId": {
                "Ref": "ApiGatewayRestApi"
              },
              "ApiKeyRequired": false,
              "AuthorizationType": "NONE",
              "Integration": {
                "IntegrationHttpMethod": "POST",
                "Type": "AWS_PROXY",
                "Uri": {
                  "Fn::Join": [
                    "",
                    [
                      "arn:aws:apigateway:",
                      {
                        "Ref": "AWS::Region"
                      },
                      ":lambda:path/2015-03-31/functions/",
                      {
                        "Fn::GetAtt": [
                          "ListLambdaFunction",
                          "Arn"
                        ]
                      },
                      "/invocations"
                    ]
                  ]
                }
              },
              "MethodResponses": []
            }
          },
          "ApiGatewayMethodShopsIdVarGet": {
            "Type": "AWS::ApiGateway::Method",
            "Properties": {
              "HttpMethod": "GET",
              "RequestParameters": {},
              "ResourceId": {
                "Ref": "ApiGatewayResourceShopsIdVar"
              },
              "RestApiId": {
                "Ref": "ApiGatewayRestApi"
              },
              "ApiKeyRequired": false,
              "AuthorizationType": "NONE",
              "Integration": {
                "IntegrationHttpMethod": "POST",
                "Type": "AWS_PROXY",
                "Uri": {
                  "Fn::Join": [
                    "",
                    [
                      "arn:aws:apigateway:",
                      {
                        "Ref": "AWS::Region"
                      },
                      ":lambda:path/2015-03-31/functions/",
                      {
                        "Fn::GetAtt": [
                          "GetLambdaFunction",
                          "Arn"
                        ]
                      },
                      "/invocations"
                    ]
                  ]
                }
              },
              "MethodResponses": []
            }
          },
          "ApiGatewayMethodShopsIdVarPut": {
            "Type": "AWS::ApiGateway::Method",
            "Properties": {
              "HttpMethod": "PUT",
              "RequestParameters": {},
              "ResourceId": {
                "Ref": "ApiGatewayResourceShopsIdVar"
              },
              "RestApiId": {
                "Ref": "ApiGatewayRestApi"
              },
              "ApiKeyRequired": false,
              "AuthorizationType": "NONE",
              "Integration": {
                "IntegrationHttpMethod": "POST",
                "Type": "AWS_PROXY",
                "Uri": {
                  "Fn::Join": [
                    "",
                    [
                      "arn:aws:apigateway:",
                      {
                        "Ref": "AWS::Region"
                      },
                      ":lambda:path/2015-03-31/functions/",
                      {
                        "Fn::GetAtt": [
                          "UpdateLambdaFunction",
                          "Arn"
                        ]
                      },
                      "/invocations"
                    ]
                  ]
                }
              },
              "MethodResponses": []
            }
          },
          "ApiGatewayMethodShopsIdVarDelete": {
            "Type": "AWS::ApiGateway::Method",
            "Properties": {
              "HttpMethod": "DELETE",
              "RequestParameters": {},
              "ResourceId": {
                "Ref": "ApiGatewayResourceShopsIdVar"
              },
              "RestApiId": {
                "Ref": "ApiGatewayRestApi"
              },
              "ApiKeyRequired": false,
              "AuthorizationType": "NONE",
              "Integration": {
                "IntegrationHttpMethod": "POST",
                "Type": "AWS_PROXY",
                "Uri": {
                  "Fn::Join": [
                    "",
                    [
                      "arn:aws:apigateway:",
                      {
                        "Ref": "AWS::Region"
                      },
                      ":lambda:path/2015-03-31/functions/",
                      {
                        "Fn::GetAtt": [
                          "DeleteLambdaFunction",
                          "Arn"
                        ]
                      },
                      "/invocations"
                    ]
                  ]
                }
              },
              "MethodResponses": []
            }
          },
          "ApiGatewayMethodShopsIdVarProductsGet": {
            "Type": "AWS::ApiGateway::Method",
            "Properties": {
              "HttpMethod": "GET",
              "RequestParameters": {},
              "ResourceId": {
                "Ref": "ApiGatewayResourceShopsIdVarProducts"
              },
              "RestApiId": {
                "Ref": "ApiGatewayRestApi"
              },
              "ApiKeyRequired": false,
              "AuthorizationType": "NONE",
              "Integration": {
                "IntegrationHttpMethod": "POST",
                "Type": "AWS_PROXY",
                "Uri": {
                  "Fn::Join": [
                    "",
                    [
                      "arn:aws:apigateway:",
                      {
                        "Ref": "AWS::Region"
                      },
                      ":lambda:path/2015-03-31/functions/",
                      {
                        "Fn::GetAtt": [
                          "GetAllProductsLambdaFunction",
                          "Arn"
                        ]
                      },
                      "/invocations"
                    ]
                  ]
                }
              },
              "MethodResponses": []
            }
          },
          "ApiGatewayDeployment1516571923373": {
            "Type": "AWS::ApiGateway::Deployment",
            "Properties": {
              "RestApiId": {
                "Ref": "ApiGatewayRestApi"
              },
              "StageName": "dev"
            },
            "DependsOn": [
              "ApiGatewayMethodShopsPost",
              "ApiGatewayMethodShopsGet",
              "ApiGatewayMethodShopsIdVarGet",
              "ApiGatewayMethodShopsIdVarPut",
              "ApiGatewayMethodShopsIdVarDelete",
              "ApiGatewayMethodShopsIdVarProductsGet"
            ]
          },
          "CreateLambdaPermissionApiGateway": {
            "Type": "AWS::Lambda::Permission",
            "Properties": {
              "FunctionName": {
                "Fn::GetAtt": [
                  "CreateLambdaFunction",
                  "Arn"
                ]
              },
              "Action": "lambda:InvokeFunction",
              "Principal": "apigateway.amazonaws.com",
              "SourceArn": {
                "Fn::Join": [
                  "",
                  [
                    "arn:aws:execute-api:",
                    {
                      "Ref": "AWS::Region"
                    },
                    ":",
                    {
                      "Ref": "AWS::AccountId"
                    },
                    ":",
                    {
                      "Ref": "ApiGatewayRestApi"
                    },
                    "/*/*"
                  ]
                ]
              }
            }
          },
          "ListLambdaPermissionApiGateway": {
            "Type": "AWS::Lambda::Permission",
            "Properties": {
              "FunctionName": {
                "Fn::GetAtt": [
                  "ListLambdaFunction",
                  "Arn"
                ]
              },
              "Action": "lambda:InvokeFunction",
              "Principal": "apigateway.amazonaws.com",
              "SourceArn": {
                "Fn::Join": [
                  "",
                  [
                    "arn:aws:execute-api:",
                    {
                      "Ref": "AWS::Region"
                    },
                    ":",
                    {
                      "Ref": "AWS::AccountId"
                    },
                    ":",
                    {
                      "Ref": "ApiGatewayRestApi"
                    },
                    "/*/*"
                  ]
                ]
              }
            }
          },
          "GetLambdaPermissionApiGateway": {
            "Type": "AWS::Lambda::Permission",
            "Properties": {
              "FunctionName": {
                "Fn::GetAtt": [
                  "GetLambdaFunction",
                  "Arn"
                ]
              },
              "Action": "lambda:InvokeFunction",
              "Principal": "apigateway.amazonaws.com",
              "SourceArn": {
                "Fn::Join": [
                  "",
                  [
                    "arn:aws:execute-api:",
                    {
                      "Ref": "AWS::Region"
                    },
                    ":",
                    {
                      "Ref": "AWS::AccountId"
                    },
                    ":",
                    {
                      "Ref": "ApiGatewayRestApi"
                    },
                    "/*/*"
                  ]
                ]
              }
            }
          },
          "UpdateLambdaPermissionApiGateway": {
            "Type": "AWS::Lambda::Permission",
            "Properties": {
              "FunctionName": {
                "Fn::GetAtt": [
                  "UpdateLambdaFunction",
                  "Arn"
                ]
              },
              "Action": "lambda:InvokeFunction",
              "Principal": "apigateway.amazonaws.com",
              "SourceArn": {
                "Fn::Join": [
                  "",
                  [
                    "arn:aws:execute-api:",
                    {
                      "Ref": "AWS::Region"
                    },
                    ":",
                    {
                      "Ref": "AWS::AccountId"
                    },
                    ":",
                    {
                      "Ref": "ApiGatewayRestApi"
                    },
                    "/*/*"
                  ]
                ]
              }
            }
          },
          "DeleteLambdaPermissionApiGateway": {
            "Type": "AWS::Lambda::Permission",
            "Properties": {
              "FunctionName": {
                "Fn::GetAtt": [
                  "DeleteLambdaFunction",
                  "Arn"
                ]
              },
              "Action": "lambda:InvokeFunction",
              "Principal": "apigateway.amazonaws.com",
              "SourceArn": {
                "Fn::Join": [
                  "",
                  [
                    "arn:aws:execute-api:",
                    {
                      "Ref": "AWS::Region"
                    },
                    ":",
                    {
                      "Ref": "AWS::AccountId"
                    },
                    ":",
                    {
                      "Ref": "ApiGatewayRestApi"
                    },
                    "/*/*"
                  ]
                ]
              }
            }
          },
          "GetAllProductsLambdaPermissionApiGateway": {
            "Type": "AWS::Lambda::Permission",
            "Properties": {
              "FunctionName": {
                "Fn::GetAtt": [
                  "GetAllProductsLambdaFunction",
                  "Arn"
                ]
              },
              "Action": "lambda:InvokeFunction",
              "Principal": "apigateway.amazonaws.com",
              "SourceArn": {
                "Fn::Join": [
                  "",
                  [
                    "arn:aws:execute-api:",
                    {
                      "Ref": "AWS::Region"
                    },
                    ":",
                    {
                      "Ref": "AWS::AccountId"
                    },
                    ":",
                    {
                      "Ref": "ApiGatewayRestApi"
                    },
                    "/*/*"
                  ]
                ]
              }
            }
          },
          "TodosDynamoDbTable": {
            "Type": "AWS::DynamoDB::Table",
            "DeletionPolicy": "Retain",
            "Properties": {
              "AttributeDefinitions": [
                {
                  "AttributeName": "id",
                  "AttributeType": "S"
                }
              ],
              "KeySchema": [
                {
                  "AttributeName": "id",
                  "KeyType": "HASH"
                }
              ],
              "ProvisionedThroughput": {
                "ReadCapacityUnits": 1,
                "WriteCapacityUnits": 1
              },
              "TableName": "shops-dev"
            }
          }
        },
        "Outputs": {
          "ServerlessDeploymentBucketName": {
            "Value": {
              "Ref": "ServerlessDeploymentBucket"
            }
          },
          "CreateLambdaFunctionQualifiedArn": {
            "Description": "Current Lambda function version",
            "Value": {
              "Ref": "CreateLambdaVersionTaP6Y24u4WQpRh3Q19TqVCd3PdTv1XU9fkvll5ztXY"
            }
          },
          "ListLambdaFunctionQualifiedArn": {
            "Description": "Current Lambda function version",
            "Value": {
              "Ref": "ListLambdaVersionYWgAFUmBX6Yv5DRatevpWHUQur1NjDe820Exzs"
            }
          },
          "GetLambdaFunctionQualifiedArn": {
            "Description": "Current Lambda function version",
            "Value": {
              "Ref": "GetLambdaVersionBH490l2TIYbIIs8R04LX8usYhs9pZbQoruYjNAQho"
            }
          },
          "UpdateLambdaFunctionQualifiedArn": {
            "Description": "Current Lambda function version",
            "Value": {
              "Ref": "UpdateLambdaVersionUR0MMhmmXWk0FtdvKuPmiCfXG3zwSZJsW6H3IkcI"
            }
          },
          "DeleteLambdaFunctionQualifiedArn": {
            "Description": "Current Lambda function version",
            "Value": {
              "Ref": "DeleteLambdaVersionvECnbEVGRTEhyz4dZHVQV94L7DoqaHTKYMoxbu4zTew"
            }
          },
          "GetAllProductsLambdaFunctionQualifiedArn": {
            "Description": "Current Lambda function version",
            "Value": {
              "Ref": "GetAllProductsLambdaVersion8WqdNfBg60zIVyAnI2XO4kg7JgFBIlYK3fOSahkAu8"
            }
          },
          "ServiceEndpoint": {
            "Description": "URL of the service endpoint",
            "Value": {
              "Fn::Join": [
                "",
                [
                  "https://",
                  {
                    "Ref": "ApiGatewayRestApi"
                  },
                  ".execute-api.us-east-1.amazonaws.com/dev"
                ]
              ]
            }
          }
        }
      },
      "coreCloudFormationTemplate": {
        "AWSTemplateFormatVersion": "2010-09-09",
        "Description": "The AWS CloudFormation template for this Serverless application",
        "Resources": {
          "ServerlessDeploymentBucket": {
            "Type": "AWS::S3::Bucket",
            "Properties": {
              "AccelerateConfiguration": {
                "AccelerationStatus": "Suspended"
              }
            }
          }
        },
        "Outputs": {
          "ServerlessDeploymentBucketName": {
            "Value": {
              "Ref": "ServerlessDeploymentBucket"
            }
          }
        }
      },
      "vpc": {}
    },
    "custom": {
      "dynamodb": {
        "start": {
          "port": 8000,
          "inMemory": true,
          "migrate": true
        },
        "migration": {
          "dir": "offline/migrations"
        }
      }
    },
    "plugins": [
      "serverless-dynamodb-local",
      "serverless-offline"
    ],
    "functions": {
      "create": {
        "handler": "create.create",
        "events": [
          {
            "http": {
              "path": "shops",
              "method": "post",
              "cors": {
                "origins": [
                  "*"
                ],
                "origin": "*",
                "methods": [
                  "OPTIONS",
                  "POST"
                ],
                "headers": [
                  "Content-Type",
                  "X-Amz-Date",
                  "Authorization",
                  "X-Api-Key",
                  "X-Amz-Security-Token",
                  "X-Amz-User-Agent"
                ],
                "allowCredentials": false
              },
              "integration": "AWS_PROXY"
            }
          }
        ],
        "name": "shops-dev-create",
        "package": {},
        "vpc": {}
      },
      "list": {
        "handler": "list.list",
        "events": [
          {
            "http": {
              "path": "shops",
              "method": "get",
              "cors": {
                "origins": [
                  "*"
                ],
                "origin": "*",
                "methods": [
                  "OPTIONS",
                  "GET"
                ],
                "headers": [
                  "Content-Type",
                  "X-Amz-Date",
                  "Authorization",
                  "X-Api-Key",
                  "X-Amz-Security-Token",
                  "X-Amz-User-Agent"
                ],
                "allowCredentials": false
              },
              "integration": "AWS_PROXY"
            }
          }
        ],
        "name": "shops-dev-list",
        "package": {},
        "vpc": {}
      },
      "get": {
        "handler": "get.get",
        "events": [
          {
            "http": {
              "path": "shops/{id}",
              "method": "get",
              "cors": {
                "origins": [
                  "*"
                ],
                "origin": "*",
                "methods": [
                  "OPTIONS",
                  "GET"
                ],
                "headers": [
                  "Content-Type",
                  "X-Amz-Date",
                  "Authorization",
                  "X-Api-Key",
                  "X-Amz-Security-Token",
                  "X-Amz-User-Agent"
                ],
                "allowCredentials": false
              },
              "integration": "AWS_PROXY"
            }
          }
        ],
        "name": "shops-dev-get",
        "package": {},
        "vpc": {}
      },
      "update": {
        "handler": "update.update",
        "events": [
          {
            "http": {
              "path": "shops/{id}",
              "method": "put",
              "cors": {
                "origins": [
                  "*"
                ],
                "origin": "*",
                "methods": [
                  "OPTIONS",
                  "PUT"
                ],
                "headers": [
                  "Content-Type",
                  "X-Amz-Date",
                  "Authorization",
                  "X-Api-Key",
                  "X-Amz-Security-Token",
                  "X-Amz-User-Agent"
                ],
                "allowCredentials": false
              },
              "integration": "AWS_PROXY"
            }
          }
        ],
        "name": "shops-dev-update",
        "package": {},
        "vpc": {}
      },
      "delete": {
        "handler": "delete.delete",
        "events": [
          {
            "http": {
              "path": "shops/{id}",
              "method": "delete",
              "cors": {
                "origins": [
                  "*"
                ],
                "origin": "*",
                "methods": [
                  "OPTIONS",
                  "DELETE"
                ],
                "headers": [
                  "Content-Type",
                  "X-Amz-Date",
                  "Authorization",
                  "X-Api-Key",
                  "X-Amz-Security-Token",
                  "X-Amz-User-Agent"
                ],
                "allowCredentials": false
              },
              "integration": "AWS_PROXY"
            }
          }
        ],
        "name": "shops-dev-delete",
        "package": {},
        "vpc": {}
      },
      "getAllProducts": {
        "handler": "getAllProducts.get",
        "events": [
          {
            "http": {
              "path": "shops/{id}/products",
              "method": "get",
              "cors": {
                "origins": [
                  "*"
                ],
                "origin": "*",
                "methods": [
                  "OPTIONS",
                  "GET"
                ],
                "headers": [
                  "Content-Type",
                  "X-Amz-Date",
                  "Authorization",
                  "X-Api-Key",
                  "X-Amz-Security-Token",
                  "X-Amz-User-Agent"
                ],
                "allowCredentials": false
              },
              "integration": "AWS_PROXY"
            }
          }
        ],
        "name": "shops-dev-getAllProducts",
        "package": {},
        "vpc": {}
      }
    },
    "resources": {
      "Resources": {
        "TodosDynamoDbTable": {
          "Type": "AWS::DynamoDB::Table",
          "DeletionPolicy": "Retain",
          "Properties": {
            "AttributeDefinitions": [
              {
                "AttributeName": "id",
                "AttributeType": "S"
              }
            ],
            "KeySchema": [
              {
                "AttributeName": "id",
                "KeyType": "HASH"
              }
            ],
            "ProvisionedThroughput": {
              "ReadCapacityUnits": 1,
              "WriteCapacityUnits": 1
            },
            "TableName": "shops-dev"
          }
        }
      },
      "Outputs": {}
    },
    "artifact": "/Users/haidang/Desktop/aws-node-rest-api-with-dynamodb-and-offline/shops/.serverless/shops.zip"
  },
  "package": {
    "artifactDirectoryName": "serverless/shops/dev/1516571923348-2018-01-21T21:58:43.348Z",
    "artifact": "shops.zip"
  }
}